[{"correlation":0.17251424,"p_value":5.686406794e-53,"lower_ci":0.1508572725,"upper_ci":0.1940056916,"feature":"onehot-genre_World cinema","col_id":"World cinema","number_of_movies":1240,"Genre":"World cinema","sem":0.0214914516},{"correlation":0.1698107558,"p_value":2.343362647e-51,"lower_ci":0.1481344386,"upper_ci":0.1913239955,"feature":"onehot-genre_Drama","col_id":"Drama","number_of_movies":4331,"Genre":"Drama","sem":0.0215132397},{"correlation":0.1663745644,"p_value":2.420413702e-49,"lower_ci":0.1446741277,"upper_ci":0.1879150337,"feature":"onehot-genre_Black-and-white","col_id":"Black-and-white","number_of_movies":145,"Genre":"Black-and-white","sem":0.0215404693},{"correlation":0.094679626,"p_value":6.102339471e-17,"lower_ci":0.0725968105,"upper_ci":0.1166696566,"feature":"onehot-genre_Art film","col_id":"Art film","number_of_movies":103,"Genre":"Art film","sem":0.0219900306},{"correlation":0.0773212969,"p_value":0.0,"lower_ci":0.0551805172,"upper_ci":0.0993860744,"feature":"onehot-genre_Documentary","col_id":"Documentary","number_of_movies":659,"Genre":"Documentary","sem":0.0220647775},{"correlation":0.076741051,"p_value":0.0,"lower_ci":0.0545985663,"upper_ci":0.098808097,"feature":"onehot-genre_Film noir","col_id":"Film noir","number_of_movies":62,"Genre":"Film noir","sem":0.022067046},{"correlation":0.0737334979,"p_value":0.0000000001,"lower_ci":0.051582417,"upper_ci":0.0958120638,"feature":"onehot-genre_New Hollywood","col_id":"New Hollywood","number_of_movies":59,"Genre":"New Hollywood","sem":0.0220785659},{"correlation":0.07024011,"p_value":0.0000000006,"lower_ci":0.0480795514,"upper_ci":0.0923315544,"feature":"onehot-genre_Biography","col_id":"Biography","number_of_movies":417,"Genre":"Biography","sem":0.0220914444},{"correlation":0.0669904465,"p_value":0.0000000034,"lower_ci":0.0448215607,"upper_ci":0.0890933861,"feature":"onehot-genre_Silent film","col_id":"Silent film","number_of_movies":11,"Genre":"Silent film","sem":0.0221029396},{"correlation":0.064334585,"p_value":0.0000000138,"lower_ci":0.0421592437,"upper_ci":0.0864465723,"feature":"onehot-genre_History","col_id":"History","number_of_movies":228,"Genre":"History","sem":0.0221119873},{"correlation":0.0516966228,"p_value":0.0000051337,"lower_ci":0.0294948765,"upper_ci":0.0738473856,"feature":"onehot-genre_Indie","col_id":"Indie","number_of_movies":1390,"Genre":"Indie","sem":0.0221507628},{"correlation":0.0490955987,"p_value":0.0000149398,"lower_ci":0.0268893021,"upper_ci":0.0712534642,"feature":"onehot-genre_War film","col_id":"War film","number_of_movies":378,"Genre":"War film","sem":0.0221578655},{"correlation":0.0473903137,"p_value":0.000029277,"lower_ci":0.0251811976,"upper_ci":0.0695526732,"feature":"onehot-genre_Existentialism","col_id":"Existentialism","number_of_movies":27,"Genre":"Existentialism","sem":0.0221623595},{"correlation":0.0468314082,"p_value":0.0000363272,"lower_ci":0.0246213961,"upper_ci":0.0689952125,"feature":"onehot-genre_Music","col_id":"Music","number_of_movies":190,"Genre":"Music","sem":0.0221638043},{"correlation":0.0454624318,"p_value":0.0000610197,"lower_ci":0.0232502843,"upper_ci":0.0676297168,"feature":"onehot-genre_Experimental film","col_id":"Experimental film","number_of_movies":53,"Genre":"Experimental film","sem":0.022167285},{"correlation":0.0440332294,"p_value":0.0001033105,"lower_ci":0.0218189415,"upper_ci":0.0662040594,"feature":"onehot-genre_Culture & Society","col_id":"Culture & Society","number_of_movies":188,"Genre":"Culture & Society","sem":0.02217083},{"correlation":0.0425611095,"p_value":0.0001749007,"lower_ci":0.0203447122,"upper_ci":0.0647354964,"feature":"onehot-genre_Ensemble Film","col_id":"Ensemble Film","number_of_movies":209,"Genre":"Ensemble Film","sem":0.0221743869},{"correlation":0.042256147,"p_value":0.0001946636,"lower_ci":0.0200393249,"upper_ci":0.0644312588,"feature":"onehot-genre_Animation","col_id":"Animation","number_of_movies":303,"Genre":"Animation","sem":0.0221751118},{"correlation":0.041965938,"p_value":0.0002154027,"lower_ci":0.0197487154,"upper_ci":0.0641417358,"feature":"onehot-genre_Musical","col_id":"Musical","number_of_movies":331,"Genre":"Musical","sem":0.0221757978},{"correlation":0.0412262157,"p_value":0.0002780316,"lower_ci":0.0190079892,"upper_ci":0.0634037449,"feature":"onehot-genre_Japanese Movies","col_id":"Japanese Movies","number_of_movies":232,"Genre":"Japanese Movies","sem":0.0221775292},{"correlation":0.0399471083,"p_value":0.0004281731,"lower_ci":0.0177272036,"upper_ci":0.0621275744,"feature":"onehot-genre_Feminist Film","col_id":"Feminist Film","number_of_movies":28,"Genre":"Feminist Film","sem":0.0221804661},{"correlation":0.0394508978,"p_value":0.0005046112,"lower_ci":0.0172303616,"upper_ci":0.0616324837,"feature":"onehot-genre_Mumblecore","col_id":"Mumblecore","number_of_movies":9,"Genre":"Mumblecore","sem":0.0221815859},{"correlation":0.0374944145,"p_value":0.0009474848,"lower_ci":0.0152714956,"upper_ci":0.0596803092,"feature":"onehot-genre_Romantic drama","col_id":"Romantic drama","number_of_movies":747,"Genre":"Romantic drama","sem":0.0221858947},{"correlation":0.0374398473,"p_value":0.0009638928,"lower_ci":0.0152168644,"upper_ci":0.0596258598,"feature":"onehot-genre_Samurai cinema","col_id":"Samurai cinema","number_of_movies":10,"Genre":"Samurai cinema","sem":0.0221860125},{"correlation":0.0368753627,"p_value":0.0011497659,"lower_ci":0.0146517254,"upper_ci":0.0590625854,"feature":"onehot-genre_Crime Drama","col_id":"Crime Drama","number_of_movies":113,"Genre":"Crime Drama","sem":0.0221872227},{"correlation":0.0358058035,"p_value":0.0015956534,"lower_ci":0.0135809653,"upper_ci":0.0579952806,"feature":"onehot-genre_Americana","col_id":"Americana","number_of_movies":47,"Genre":"Americana","sem":0.0221894771},{"correlation":0.0348859214,"p_value":0.0021011348,"lower_ci":0.012660091,"upper_ci":0.0570772969,"feature":"onehot-genre_Political drama","col_id":"Political drama","number_of_movies":224,"Genre":"Political drama","sem":0.0221913755},{"correlation":0.0343977399,"p_value":0.0024254686,"lower_ci":0.0121713983,"upper_ci":0.0565901075,"feature":"onehot-genre_Comedy-drama","col_id":"Comedy-drama","number_of_movies":571,"Genre":"Comedy-drama","sem":0.0221923676},{"correlation":0.03427363,"p_value":0.0025149247,"lower_ci":0.0120471601,"upper_ci":0.0564662482,"feature":"onehot-genre_Marriage Drama","col_id":"Marriage Drama","number_of_movies":48,"Genre":"Marriage Drama","sem":0.0221926182},{"correlation":0.034202963,"p_value":0.0025671983,"lower_ci":0.0119764204,"upper_ci":0.0563957236,"feature":"onehot-genre_Avant-garde","col_id":"Avant-garde","number_of_movies":46,"Genre":"Avant-garde","sem":0.0221927606},{"correlation":0.0341338715,"p_value":0.0026192652,"lower_ci":0.011907258,"upper_ci":0.056326771,"feature":"onehot-genre_Law & Crime","col_id":"Law & Crime","number_of_movies":23,"Genre":"Law & Crime","sem":0.0221928995},{"correlation":0.0339449619,"p_value":0.0027665917,"lower_ci":0.0117181557,"upper_ci":0.0561382403,"feature":"onehot-genre_Comedy of manners","col_id":"Comedy of manners","number_of_movies":107,"Genre":"Comedy of manners","sem":0.0221932784},{"correlation":0.033579719,"p_value":0.0030730934,"lower_ci":0.0113525446,"upper_ci":0.0557737255,"feature":"onehot-genre_Biographical film","col_id":"Biographical film","number_of_movies":243,"Genre":"Biographical film","sem":0.0221940065},{"correlation":0.0313552037,"p_value":0.0057076374,"lower_ci":0.0091259153,"upper_ci":0.0535535169,"feature":"onehot-genre_Combat Films","col_id":"Combat Films","number_of_movies":19,"Genre":"Combat Films","sem":0.0221983132},{"correlation":0.031111748,"p_value":0.0060945852,"lower_ci":0.0088822417,"upper_ci":0.0533105193,"feature":"onehot-genre_Family Drama","col_id":"Family Drama","number_of_movies":280,"Genre":"Family Drama","sem":0.0221987713},{"correlation":0.0310899847,"p_value":0.0061303007,"lower_ci":0.008860459,"upper_ci":0.0532887968,"feature":"onehot-genre_Film","col_id":"Film","number_of_movies":30,"Genre":"Film","sem":0.0221988121},{"correlation":0.0305073024,"p_value":0.0071593703,"lower_ci":0.0082772663,"upper_ci":0.0527071994,"feature":"onehot-genre_Essay Film","col_id":"Essay Film","number_of_movies":7,"Genre":"Essay Film","sem":0.022199897},{"correlation":0.0303869136,"p_value":0.00739039,"lower_ci":0.008156774,"upper_ci":0.0525870329,"feature":"onehot-genre_Star vehicle","col_id":"Star vehicle","number_of_movies":2,"Genre":"Star vehicle","sem":0.0222001193},{"correlation":0.0291228461,"p_value":0.0102511467,"lower_ci":0.006891658,"upper_ci":0.0513252606,"feature":"onehot-genre_British New Wave","col_id":"British New Wave","number_of_movies":2,"Genre":"British New Wave","sem":0.0222024145},{"correlation":0.0286549343,"p_value":0.0115377342,"lower_ci":0.0064233761,"upper_ci":0.0508581804,"feature":"onehot-genre_Graphic & Applied Arts","col_id":"Graphic & Applied Arts","number_of_movies":13,"Genre":"Graphic & Applied Arts","sem":0.0222032461},{"correlation":0.0279209479,"p_value":0.0138454441,"lower_ci":0.0056888288,"upper_ci":0.0501254789,"feature":"onehot-genre_Animated Musical","col_id":"Animated Musical","number_of_movies":27,"Genre":"Animated Musical","sem":0.022204531},{"correlation":0.0273943086,"p_value":0.0157435364,"lower_ci":0.0051618018,"upper_ci":0.0495997468,"feature":"onehot-genre_Biopic [feature]","col_id":"Biopic [feature]","number_of_movies":103,"Genre":"Biopic [feature]","sem":0.0222054382},{"correlation":0.0270953155,"p_value":0.0169200093,"lower_ci":0.0048625942,"upper_ci":0.0493012633,"feature":"onehot-genre_Pre-Code","col_id":"Pre-Code","number_of_movies":6,"Genre":"Pre-Code","sem":0.0222059478},{"correlation":0.0270396114,"p_value":0.0171475221,"lower_ci":0.0048068505,"upper_ci":0.0492456537,"feature":"onehot-genre_Concert film","col_id":"Concert film","number_of_movies":26,"Genre":"Concert film","sem":0.0222060423},{"correlation":0.0270169185,"p_value":0.0172409732,"lower_ci":0.0047841416,"upper_ci":0.0492229993,"feature":"onehot-genre_Surrealism","col_id":"Surrealism","number_of_movies":37,"Genre":"Surrealism","sem":0.0222060808},{"correlation":0.02689688,"p_value":0.0177427683,"lower_ci":0.0046640185,"upper_ci":0.0491031639,"feature":"onehot-genre_Propaganda film","col_id":"Propaganda film","number_of_movies":3,"Genre":"Propaganda film","sem":0.0222062839},{"correlation":0.0265837713,"p_value":0.0191123253,"lower_ci":0.0043506921,"upper_ci":0.0487905818,"feature":"onehot-genre_Period piece","col_id":"Period piece","number_of_movies":653,"Genre":"Period piece","sem":0.0222068105},{"correlation":0.0260086296,"p_value":0.0218700468,"lower_ci":0.0037751619,"upper_ci":0.0482163961,"feature":"onehot-genre_Social issues","col_id":"Social issues","number_of_movies":84,"Genre":"Social issues","sem":0.0222077665},{"correlation":0.0259380508,"p_value":0.02223123,"lower_ci":0.0037045365,"upper_ci":0.0481459336,"feature":"onehot-genre_Interpersonal Relationships","col_id":"Interpersonal Relationships","number_of_movies":21,"Genre":"Interpersonal Relationships","sem":0.0222078828},{"correlation":0.0257515837,"p_value":0.0232105206,"lower_ci":0.0035179471,"upper_ci":0.0479597727,"feature":"onehot-genre_Docudrama","col_id":"Docudrama","number_of_movies":76,"Genre":"Docudrama","sem":0.022208189},{"correlation":0.0248859761,"p_value":0.028262313,"lower_ci":0.0026517925,"upper_ci":0.0470955664,"feature":"onehot-genre_Neo-noir","col_id":"Neo-noir","number_of_movies":35,"Genre":"Neo-noir","sem":0.0222095903},{"correlation":0.0243798375,"p_value":0.0316345675,"lower_ci":0.0021453496,"upper_ci":0.0465902318,"feature":"onehot-genre_Political cinema","col_id":"Political cinema","number_of_movies":174,"Genre":"Political cinema","sem":0.0222103943},{"correlation":0.0237484018,"p_value":0.0363203208,"lower_ci":0.0015135501,"upper_ci":0.0459597832,"feature":"onehot-genre_British Empire Film","col_id":"British Empire Film","number_of_movies":7,"Genre":"British Empire Film","sem":0.0222113814},{"correlation":0.0236163799,"p_value":0.0373714642,"lower_ci":0.0013814544,"upper_ci":0.0458279654,"feature":"onehot-genre_Roadshow theatrical release","col_id":"Roadshow theatrical release","number_of_movies":12,"Genre":"Roadshow theatrical release","sem":0.0222115855},{"correlation":0.0236163799,"p_value":0.0373714642,"lower_ci":0.0013814544,"upper_ci":0.0458279654,"feature":"onehot-genre_Wuxia","col_id":"Wuxia","number_of_movies":12,"Genre":"Wuxia","sem":0.0222115855},{"correlation":0.0234697792,"p_value":0.038568907,"lower_ci":0.0012347726,"upper_ci":0.0456815905,"feature":"onehot-genre_Stop motion","col_id":"Stop motion","number_of_movies":32,"Genre":"Stop motion","sem":0.0222118113},{"correlation":0.0232729561,"p_value":0.0402277097,"lower_ci":0.0010378422,"upper_ci":0.045485069,"feature":"onehot-genre_Foreign legion","col_id":"Foreign legion","number_of_movies":1,"Genre":"Foreign legion","sem":0.0222121129},{"correlation":0.0231542225,"p_value":0.0412573437,"lower_ci":0.0009190447,"upper_ci":0.0453665165,"feature":"onehot-genre_Coming of age","col_id":"Coming of age","number_of_movies":350,"Genre":"Coming of age","sem":0.022212294},{"correlation":0.0229250794,"p_value":0.0433075942,"lower_ci":0.0006897801,"upper_ci":0.0451377212,"feature":"onehot-genre_Chinese Movies","col_id":"Chinese Movies","number_of_movies":131,"Genre":"Chinese Movies","sem":0.0222126418},{"correlation":0.0224529408,"p_value":0.0478043015,"lower_ci":0.0002173984,"upper_ci":0.0446662918,"feature":"onehot-genre_Fairy tale","col_id":"Fairy tale","number_of_movies":13,"Genre":"Fairy tale","sem":0.022213351},{"correlation":-0.0226975723,"p_value":0.0454277024,"lower_ci":-0.0449105571,"upper_ci":-0.0004621546,"feature":"onehot-genre_Road-Horror","col_id":"Road-Horror","number_of_movies":13,"Genre":"Road-Horror","sem":0.0222354177},{"correlation":-0.0240847506,"p_value":0.0337555776,"lower_ci":-0.0462956084,"upper_ci":-0.0018500904,"feature":"onehot-genre_Adventure","col_id":"Adventure","number_of_movies":887,"Genre":"Adventure","sem":0.0222346602},{"correlation":-0.0242393154,"p_value":0.0326299128,"lower_ci":-0.0464499309,"upper_ci":-0.002004745,"feature":"onehot-genre_Sword and sorcery films","col_id":"Sword and sorcery films","number_of_movies":16,"Genre":"Sword and sorcery films","sem":0.0222345704},{"correlation":-0.0253888923,"p_value":0.0252229677,"lower_ci":-0.0475976726,"upper_ci":-0.0031550225,"feature":"onehot-genre_Time travel","col_id":"Time travel","number_of_movies":47,"Genre":"Time travel","sem":0.0222338698},{"correlation":-0.0261828739,"p_value":0.021000143,"lower_ci":-0.0483903523,"upper_ci":-0.0039495223,"feature":"onehot-genre_Bollywood","col_id":"Bollywood","number_of_movies":31,"Genre":"Bollywood","sem":0.0222333516},{"correlation":-0.0263520631,"p_value":0.0201844797,"lower_ci":-0.0485592605,"upper_ci":-0.0041188256,"feature":"onehot-genre_Alien Film","col_id":"Alien Film","number_of_movies":27,"Genre":"Alien Film","sem":0.0222332375},{"correlation":-0.026445426,"p_value":0.019746319,"lower_ci":-0.0486524678,"upper_ci":-0.004212252,"feature":"onehot-genre_Martial Arts Film","col_id":"Martial Arts Film","number_of_movies":128,"Genre":"Martial Arts Film","sem":0.022233174},{"correlation":-0.0265575831,"p_value":0.0192309545,"lower_ci":-0.0487644374,"upper_ci":-0.0043244858,"feature":"onehot-genre_Caper story","col_id":"Caper story","number_of_movies":32,"Genre":"Caper story","sem":0.0222330973},{"correlation":-0.0272102968,"p_value":0.016458752,"lower_ci":-0.0494160491,"upper_ci":-0.0049776575,"feature":"onehot-genre_Stoner film","col_id":"Stoner film","number_of_movies":26,"Genre":"Stoner film","sem":0.0222326393},{"correlation":-0.0319052711,"p_value":0.0049137131,"lower_ci":-0.0541025398,"upper_ci":-0.009676485,"feature":"onehot-genre_Cult","col_id":"Cult","number_of_movies":306,"Genre":"Cult","sem":0.0222287861},{"correlation":-0.0323052105,"p_value":0.004400709,"lower_ci":-0.0545017113,"upper_ci":-0.010076798,"feature":"onehot-genre_Sports","col_id":"Sports","number_of_movies":284,"Genre":"Sports","sem":0.0222284125},{"correlation":-0.0323423201,"p_value":0.0043556595,"lower_ci":-0.0545387494,"upper_ci":-0.0101139427,"feature":"onehot-genre_Christmas movie","col_id":"Christmas movie","number_of_movies":30,"Genre":"Christmas movie","sem":0.0222283774},{"correlation":-0.0326242741,"p_value":0.0040268027,"lower_ci":-0.0548201573,"upper_ci":-0.0103961648,"feature":"onehot-genre_Fantasy Adventure","col_id":"Fantasy Adventure","number_of_movies":86,"Genre":"Fantasy Adventure","sem":0.0222281093},{"correlation":-0.0333040379,"p_value":0.0033246016,"lower_ci":-0.0554985901,"upper_ci":-0.0110765896,"feature":"onehot-genre_Comedy of Errors","col_id":"Comedy of Errors","number_of_movies":58,"Genre":"Comedy of Errors","sem":0.0222274483},{"correlation":-0.0338611607,"p_value":0.002834338,"lower_ci":-0.0560546068,"upper_ci":-0.0116342695,"feature":"onehot-genre_Sword and sorcery","col_id":"Sword and sorcery","number_of_movies":13,"Genre":"Sword and sorcery","sem":0.0222268912},{"correlation":-0.0350455821,"p_value":0.0020040188,"lower_ci":-0.0572366308,"upper_ci":-0.0128199213,"feature":"onehot-genre_Science Fiction","col_id":"Science Fiction","number_of_movies":623,"Genre":"Science Fiction","sem":0.0222256608},{"correlation":-0.037412469,"p_value":0.0009722241,"lower_ci":-0.0595985405,"upper_ci":-0.0151894541,"feature":"onehot-genre_Psychological thriller","col_id":"Psychological thriller","number_of_movies":403,"Genre":"Psychological thriller","sem":0.0222230149},{"correlation":-0.0405172736,"p_value":0.0003537343,"lower_ci":-0.0626964396,"upper_ci":-0.018298108,"feature":"onehot-genre_Inspirational Drama","col_id":"Inspirational Drama","number_of_movies":15,"Genre":"Inspirational Drama","sem":0.0222191656},{"correlation":-0.0439555388,"p_value":0.0001062639,"lower_ci":-0.066126559,"upper_ci":-0.0217411372,"feature":"onehot-genre_Crime Comedy","col_id":"Crime Comedy","number_of_movies":79,"Genre":"Crime Comedy","sem":0.0222144016},{"correlation":-0.0441003781,"p_value":0.0001008204,"lower_ci":-0.0662710436,"upper_ci":-0.0218861888,"feature":"onehot-genre_Crime Thriller","col_id":"Crime Thriller","number_of_movies":576,"Genre":"Crime Thriller","sem":0.0222141893},{"correlation":-0.045422836,"p_value":0.0000619291,"lower_ci":-0.0675902204,"upper_ci":-0.023210628,"feature":"onehot-genre_Screwball comedy","col_id":"Screwball comedy","number_of_movies":82,"Genre":"Screwball comedy","sem":0.022212208},{"correlation":-0.046253288,"p_value":0.0000452993,"lower_ci":-0.0684185724,"upper_ci":-0.024042364,"feature":"onehot-genre_Action Comedy","col_id":"Action Comedy","number_of_movies":61,"Genre":"Action Comedy","sem":0.022210924},{"correlation":-0.0463094815,"p_value":0.0000443426,"lower_ci":-0.0684746226,"upper_ci":-0.0240986454,"feature":"onehot-genre_Sex comedy","col_id":"Sex comedy","number_of_movies":94,"Genre":"Sex comedy","sem":0.0222108361},{"correlation":-0.0513137428,"p_value":0.0000060271,"lower_ci":-0.07346557,"upper_ci":-0.0291113077,"feature":"onehot-genre_Buddy film","col_id":"Buddy film","number_of_movies":188,"Genre":"Buddy film","sem":0.0222024351},{"correlation":-0.0558298865,"p_value":0.0000008465,"lower_ci":-0.077968746,"upper_ci":-0.0336359918,"feature":"onehot-genre_Action Thrillers","col_id":"Action Thrillers","number_of_movies":149,"Genre":"Action Thrillers","sem":0.0221938947},{"correlation":-0.0595209687,"p_value":0.0000001517,"lower_ci":-0.0816485588,"upper_ci":-0.0373347298,"feature":"onehot-genre_Supernatural","col_id":"Supernatural","number_of_movies":187,"Genre":"Supernatural","sem":0.0221862389},{"correlation":-0.0672883075,"p_value":0.0000000029,"lower_ci":-0.0893902128,"upper_ci":-0.0451201653,"feature":"onehot-genre_Romantic comedy","col_id":"Romantic comedy","number_of_movies":706,"Genre":"Romantic comedy","sem":0.0221681422},{"correlation":-0.0725474673,"p_value":0.0000000002,"lower_ci":-0.094630466,"upper_ci":-0.0503931075,"feature":"onehot-genre_Gross out","col_id":"Gross out","number_of_movies":41,"Genre":"Gross out","sem":0.0221543598},{"correlation":-0.0725474673,"p_value":0.0000000002,"lower_ci":-0.094630466,"upper_ci":-0.0503931075,"feature":"onehot-genre_Gross-out film","col_id":"Gross-out film","number_of_movies":41,"Genre":"Gross-out film","sem":0.0221543598},{"correlation":-0.082429949,"p_value":0.0,"lower_ci":-0.1044741111,"upper_ci":-0.0603048298,"feature":"onehot-genre_Horror","col_id":"Horror","number_of_movies":721,"Genre":"Horror","sem":0.0221251192},{"correlation":-0.0838254304,"p_value":0.0,"lower_ci":-0.1058637605,"upper_ci":-0.0617047919,"feature":"onehot-genre_Slasher","col_id":"Slasher","number_of_movies":161,"Genre":"Slasher","sem":0.0221206385},{"correlation":-0.0884924315,"p_value":0.0,"lower_ci":-0.1105106322,"upper_ci":-0.0663874102,"feature":"onehot-genre_Teen","col_id":"Teen","number_of_movies":314,"Genre":"Teen","sem":0.0221050213},{"correlation":-0.0888979428,"p_value":0.0,"lower_ci":-0.1109143489,"upper_ci":-0.0667943244,"feature":"onehot-genre_Comedy","col_id":"Comedy","number_of_movies":2667,"Genre":"Comedy","sem":0.0221036184},{"correlation":-0.0895700763,"p_value":0.0,"lower_ci":-0.1115834921,"upper_ci":-0.0674687995,"feature":"onehot-genre_Thriller","col_id":"Thriller","number_of_movies":1928,"Genre":"Thriller","sem":0.0221012768},{"correlation":-0.0975254515,"p_value":6.945748019e-18,"lower_ci":-0.1195019575,"upper_ci":-0.0754534245,"feature":"onehot-genre_Slapstick","col_id":"Slapstick","number_of_movies":149,"Genre":"Slapstick","sem":0.022072027},{"correlation":-0.1144630107,"p_value":4.444883376e-24,"lower_ci":-0.136351625,"upper_ci":-0.0924626921,"feature":"onehot-genre_Action\/Adventure","col_id":"Action\/Adventure","number_of_movies":1018,"Genre":"Action\/Adventure","sem":0.0220003186},{"correlation":-0.1411352077,"p_value":7.339505907e-36,"lower_ci":-0.1628597668,"upper_ci":-0.119273866,"feature":"onehot-genre_Action","col_id":"Action","number_of_movies":1395,"Genre":"Action","sem":0.0218613417}]